volta/__init__.py
volta/cli.py
volta/components.py
volta/dom_renderer.py
volta/element.py
volta/events.py
volta/hooks.py
volta/html_renderer.py
volta/loader.py
volta/logo.svg
volta/reconciler.py
volta/renderer.py
volta/router.py
volta/runtime.py
volta/security.py
volta/transpiler.py
volta_framework-0.1.3.dist-info/licenses/LICENSE
volta_framework-0.1.3.dist-info/METADATA
volta_framework-0.1.3.dist-info/WHEEL
volta_framework-0.1.3.dist-info/entry_points.txt
volta_framework-0.1.3.dist-info/top_level.txt
volta_framework-0.1.3.dist-info/RECORD
