Metadata-Version: 2.4
Name: volta-framework
Version: 0.1.3
Summary: A Python UI framework mimicking React
Home-page: https://github.com/onyedibia/volta
Author: Shinkilabs Nigeria Limited
Author-email: Shinkilabs Nigeria Limited <shinkilabs@gmail.com>
Project-URL: Homepage, https://github.com/onyedibia/volta
Classifier: Programming Language :: Python :: 3
Classifier: License :: OSI Approved :: MIT License
Classifier: Operating System :: OS Independent
Requires-Python: >=3.8, <4
License-File: LICENSE
Dynamic: author
Dynamic: home-page
Dynamic: license-file
Dynamic: requires-python
